{
  "info": {
    "name": "DonationPlatform API",
    "_postman_id": "bc02f134-1abc-4cfc-8c03-00d82120399c",
    "description": "API untuk menguji DonationPlatform Smart Contract via Flask Backend",
    "schema": "https://schema.getpostman.com/json/collection/v2.1.0/collection.json"
  },
  "item": [
    {
      "name": "Test Blockchain",
      "request": {
        "method": "GET",
        "header": [],
        "url": "http://127.0.0.1:5000/test"
      }
    },
    {
      "name": "Create Campaign",
      "request": {
        "method": "POST",
        "header": [
          { "key": "Content-Type", "value": "application/json" }
        ],
        "body": {
          "mode": "raw",
          "raw": "{\n    \"title\": \"Bantu Sekolah Desa\",\n    \"duration\": 60,\n    \"from\": \"0xYOUR_ADDRESS\",\n    \"private_key\": \"YOUR_PRIVATE_KEY\"\n}"
        },
        "url": "http://127.0.0.1:5000/create-campaign"
      }
    },
    {
      "name": "Get All Campaigns",
      "request": {
        "method": "GET",
        "url": "http://127.0.0.1:5000/campaigns"
      }
    },
    {
      "name": "Get Campaign Detail",
      "request": {
        "method": "GET",
        "url": "http://127.0.0.1:5000/campaign/0"
      }
    },
    {
      "name": "Donate to Campaign",
      "request": {
        "method": "POST",
        "header": [
          { "key": "Content-Type", "value": "application/json" }
        ],
        "body": {
          "mode": "raw",
          "raw": "{\n    \"campaign_id\": 0,\n    \"amount\": 0.01,\n    \"from\": \"0xYOUR_ADDRESS\",\n    \"private_key\": \"YOUR_PRIVATE_KEY\"\n}"
        },
        "url": "http://127.0.0.1:5000/donate"
      }
    },
    {
      "name": "Admin Approve",
      "request": {
        "method": "POST",
        "header": [
          { "key": "Content-Type", "value": "application/json" }
        ],
        "body": {
          "mode": "raw",
          "raw": "{\n    \"campaign_id\": 0,\n    \"from\": \"0xADMIN\",\n    \"private_key\": \"ADMIN_PRIVATE_KEY\"\n}"
        },
        "url": "http://127.0.0.1:5000/admin/approve"
      }
    },
    {
      "name": "Admin Reject",
      "request": {
        "method": "POST",
        "header": [
          { "key": "Content-Type", "value": "application/json" }
        ],
        "body": {
          "mode": "raw",
          "raw": "{\n    \"campaign_id\": 0,\n    \"from\": \"0xADMIN\",\n    \"private_key\": \"ADMIN_PRIVATE_KEY\"\n}"
        },
        "url": "http://127.0.0.1:5000/admin/reject"
      }
    },
    {
      "name": "Admin Disable",
      "request": {
        "method": "POST",
        "header": [
          { "key": "Content-Type", "value": "application/json" }
        ],
        "body": {
          "mode": "raw",
          "raw": "{\n    \"campaign_id\": 0,\n    \"from\": \"0xADMIN\",\n    \"private_key\": \"ADMIN_PRIVATE_KEY\"\n}"
        },
        "url": "http://127.0.0.1:5000/admin/disable"
      }
    },
    {
      "name": "Withdraw Funds",
      "request": {
        "method": "POST",
        "header": [
          { "key": "Content-Type", "value": "application/json" }
        ],
        "body": {
          "mode": "raw",
          "raw": "{\n    \"campaign_id\": 0,\n    \"from\": \"0xCREATOR\",\n    \"private_key\": \"CREATOR_PRIVATE_KEY\"\n}"
        },
        "url": "http://127.0.0.1:5000/withdraw"
      }
    }
  ]
}
